drongo/__init__.py
drongo/app.py
drongo/exceptions.py
drongo/request.py
drongo/response.py
drongo/response_headers.py
drongo/status_codes.py
drongo/addons/__init__.py
drongo/addons/database/__init__.py
drongo/addons/database/databases/__init__.py
drongo/addons/database/databases/_mongo.py
drongo/addons/database/databases/_postgres.py
drongo/addons/database/databases/_redis.py
drongo/client/__init__.py
drongo/managers/__init__.py
drongo/managers/middleware.py
drongo/managers/url.py
drongo/module/__init__.py
drongo/nest/__init__.py
drongo/nest/cmd.py
drongo/nest/nest.py
drongo/nest/reloader.py
drongo/nest/handlers/__init__.py
drongo/nest/handlers/asynch.py
drongo/nest/handlers/sync.py
drongo/nest/parsers/__init__.py
drongo/nest/parsers/header.py
drongo/nest/parsers/http.py
drongo/nest/parsers/request.py
drongo/nest/parsers/body/__init__.py
drongo/nest/parsers/body/body.py
drongo/nest/parsers/body/multipart.py
drongo/nest/parsers/body/raw.py
drongo/nest/parsers/body/urlencoded.py
drongo/nest/parsers/body/utils.py
drongo/utils/__init__.py
drongo/utils/dict2.py
drongo/utils/endpoint.py
drongo/utils/helpers.py
drongopy_core-0.0.3.dist-info/LICENSE
drongopy_core-0.0.3.dist-info/METADATA
drongopy_core-0.0.3.dist-info/WHEEL
drongopy_core-0.0.3.dist-info/entry_points.txt
drongopy_core-0.0.3.dist-info/top_level.txt
drongopy_core-0.0.3.dist-info/zip-safe
drongopy_core-0.0.3.dist-info/RECORD
